LICENSE
MANIFEST.in
README.md
pyproject.toml
setup.cfg
wagtailtwbsicons/__init__.py
wagtailtwbsicons/wagtail_hooks.py
wagtailtwbsicons.egg-info/PKG-INFO
wagtailtwbsicons.egg-info/SOURCES.txt
wagtailtwbsicons.egg-info/dependency_links.txt
wagtailtwbsicons.egg-info/requires.txt
wagtailtwbsicons.egg-info/top_level.txt
wagtailtwbsicons/templates/wagtailtwbsicons/0-circle-fill.svg
wagtailtwbsicons/templates/wagtailtwbsicons/0-circle.svg
wagtailtwbsicons/templates/wagtailtwbsicons/0-square-fill.svg
wagtailtwbsicons/templates/wagtailtwbsicons/0-square.svg
wagtailtwbsicons/templates/wagtailtwbsicons/1-circle-fill.svg
wagtailtwbsicons/templates/wagtailtwbsicons/1-circle.svg
wagtailtwbsicons/templates/wagtailtwbsicons/1-square-fill.svg
wagtailtwbsicons/templates/wagtailtwbsicons/1-square.svg
wagtailtwbsicons/templates/wagtailtwbsicons/123.svg
wagtailtwbsicons/templates/wagtailtwbsicons/2-circle-fill.svg
wagtailtwbsicons/templates/wagtailtwbsicons/2-circle.svg
wagtailtwbsicons/templates/wagtailtwbsicons/2-square-fill.svg
wagtailtwbsicons/templates/wagtailtwbsicons/2-square.svg
wagtailtwbsicons/templates/wagtailtwbsicons/3-circle-fill.svg
wagtailtwbsicons/templates/wagtailtwbsicons/3-circle.svg
wagtailtwbsicons/templates/wagtailtwbsicons/3-square-fill.svg
wagtailtwbsicons/templates/wagtailtwbsicons/3-square.svg
wagtailtwbsicons/templates/wagtailtwbsicons/4-circle-fill.svg
wagtailtwbsicons/templates/wagtailtwbsicons/4-circle.svg
wagtailtwbsicons/templates/wagtailtwbsicons/4-square-fill.svg
wagtailtwbsicons/templates/wagtailtwbsicons/4-square.svg
wagtailtwbsicons/templates/wagtailtwbsicons/5-circle-fill.svg
wagtailtwbsicons/templates/wagtailtwbsicons/5-circle.svg
wagtailtwbsicons/templates/wagtailtwbsicons/5-square-fill.svg
wagtailtwbsicons/templates/wagtailtwbsicons/5-square.svg
wagtailtwbsicons/templates/wagtailtwbsicons/6-circle-fill.svg
wagtailtwbsicons/templates/wagtailtwbsicons/6-circle.svg
wagtailtwbsicons/templates/wagtailtwbsicons/6-square-fill.svg
wagtailtwbsicons/templates/wagtailtwbsicons/6-square.svg
wagtailtwbsicons/templates/wagtailtwbsicons/7-circle-fill.svg
wagtailtwbsicons/templates/wagtailtwbsicons/7-circle.svg
